dify_mcp_server/__init__.py
dify_mcp_server/server.py
mseep_dify_mcp_server-0.1.5.dist-info/METADATA
mseep_dify_mcp_server-0.1.5.dist-info/WHEEL
mseep_dify_mcp_server-0.1.5.dist-info/entry_points.txt
mseep_dify_mcp_server-0.1.5.dist-info/RECORD
